akapy/__init__.py
akapy/auth.py
akapy/cloudlets/__init__.py
akapy/cloudlets/cloudlet.py
akapy/requester.py
akapy-0.3.1.dist-info/LICENSE
akapy-0.3.1.dist-info/METADATA
akapy-0.3.1.dist-info/WHEEL
akapy-0.3.1.dist-info/RECORD
